<?xml version="1.0" encoding="UTF-8"?>
<song xmlns="http://openlyrics.info/namespace/2009/song" version="0.8" createdIn="OpenLP 3.0.2" modifiedIn="OpenLP 3.0.2" modifiedDate="2024-11-06T11:31:45">
  <properties>
    <titles>
      <title>500 - Take Time to Be Holy</title>
    </titles>
    <copyright>2024</copyright>
    <verseOrder>v1 v2 v3 v4</verseOrder>
    <ccliNo>500</ccliNo>
    <authors>
      <author>UNKNOWN</author>
    </authors>
    <songbooks>
      <songbook name="SDA Hymnal"/>
    </songbooks>
    <themes>
      <theme>UNKNOWN</theme>
    </themes>
  </properties>
  <lyrics>
    <verse name="v1">
      <lines>Take time to be holy,<br/>speak oft with thy Lord;<br/>abide in him always,<br/>and feed on his word.<br/>Make friends of God’s children,<br/>help those who are weak,<br/>forgetting in nothing<br/>his blessing to seek.</lines>
    </verse>
    <verse name="v2">
      <lines>Take time to be holy,<br/>the world rushes on;<br/>spend much time in secret<br/>with Jesus alone.<br/>By looking to Jesus,<br/>like him thou shalt be;<br/>thy friends in thy conduct<br/>his likeness shall see.</lines>
    </verse>
    <verse name="v3">
      <lines>Take time to be holy,<br/>let him be thy guide,<br/>and run not before him,<br/>whatever betide.<br/>In joy or in sorrow,<br/>still follow the Lord,<br/>and, looking to Jesus,<br/>still trust in his word.</lines>
    </verse>
    <verse name="v4">
      <lines>Take time to be holy,<br/>be calm in thy soul,<br/>each thought and each motive<br/>beneath his control.<br/>Thus led by his spirit<br/>to fountains of love,<br/>thou soon shalt be fitted<br/>for service above.</lines>
    </verse>
  </lyrics>
</song>
