<?xml version="1.0" encoding="UTF-8"?>
<song xmlns="http://openlyrics.info/namespace/2009/song" version="0.8" createdIn="OpenLP 3.0.2" modifiedIn="OpenLP 3.0.2" modifiedDate="2024-11-06T11:30:38">
  <properties>
    <titles>
      <title>INJAO MIROHONDROHONA</title>
    </titles>
    <copyright>2024</copyright>
    <verseOrder>v1 v2 v3 v4</verseOrder>
    <ccliNo>474</ccliNo>
    <authors>
      <author>E. Razafiniavo</author>
    </authors>
    <songbooks>
      <songbook name="Fihirana Advantista"/>
    </songbooks>
    <themes>
      <theme>FIAINANA KRISTIANA</theme>
    </themes>
  </properties>
  <lyrics>
    <verse name="v1">
      <lines>Injao mirohondrohona<br/>Ny ranomasim-be<br/>Ny onja manoloana<br/>Mamely mafy re<br/>Ka very hevitra<br/>Ny firenena re.<br/>Ny feon'ny rivotra<br/>Mihamitsoka re.</lines>
    </verse>
    <verse name="v2">
      <lines>Tsy misy raha eto<br/>'Zay mandry fahizay<br/>fa ady mampisento<br/>Sy tebiteby indray.<br/>Eo aminao, Jeso,<br/>No fiadanana.<br/>Mionona e ny fo,<br/>Fahasambarana.</lines>
    </verse>
    <verse name="v3">
      <lines>Ny fon'ny manan-daza<br/>Ho reraka izao,<br/>Matahotra ny loza<br/>Hitranga ao ho ao.<br/>Mikaroka ny soa<br/>Dia fiadanana<br/>Kanefa ny mifoha<br/>Fikorontanana.</lines>
    </verse>
    <verse name="v4">
      <lines>Ianao irery Tompo<br/>No iantsampazako,<br/>Raha he mifofofo<br/>Ny onja tazako,<br/>Ianao ry Jeso tia<br/>Tsy atakaloko,<br/>Fihiniko satria<br/>Mpanonjy aroko.</lines>
    </verse>
  </lyrics>
</song>
